numbersystem/__init__.py
numbersystem-0.1.3.dist-info/LICENSE
numbersystem-0.1.3.dist-info/METADATA
numbersystem-0.1.3.dist-info/WHEEL
numbersystem-0.1.3.dist-info/top_level.txt
numbersystem-0.1.3.dist-info/RECORD
