Metadata-Version: 2.1
Name: numbersystem
Version: 0.1.3
Summary: This is a python library that converts the decimal number in binary, octal, and hexadecimal or vice versa.
Home-page: https://github.com/number-system
Author: Ritul Singh
Author-email: ritulsingh00@gmail.com
License: MIT
Keywords: numbersystem
Platform: UNKNOWN
Classifier: Programming Language :: Python :: 3
Classifier: License :: OSI Approved :: MIT License
Classifier: Operating System :: Microsoft :: Windows :: Windows 10
Requires-Python: >=3.6
